metaom/__init__.py
metaom/app/__init__.py
metaom/app/detection.py
metaom/app/segment.py
metaom/model_zoo/__init__.py
metaom/model_zoo/model.py
metaom/utils/__init__.py
metaom/utils/general.py
meta_om-0.1.1.dist-info/METADATA
meta_om-0.1.1.dist-info/WHEEL
meta_om-0.1.1.dist-info/top_level.txt
meta_om-0.1.1.dist-info/zip-safe
meta_om-0.1.1.dist-info/RECORD
