Metadata-Version: 2.4
Name: meta-om
Version: 0.1.1
Summary: Meta OM Toolkit
Home-page: https://github.com/CachCheng/metaom
Author: CachCheng
Author-email: tkggpdc2007@163.com
License: Apache-2.0
Requires-Dist: opencv-python
Requires-Dist: setuptools
Requires-Dist: numpy
Requires-Dist: meta-cv
Dynamic: author
Dynamic: author-email
Dynamic: description
Dynamic: description-content-type
Dynamic: home-page
Dynamic: license
Dynamic: requires-dist
Dynamic: summary
